configure_gpu/__init__.py
configure_gpu-0.1.dist-info/METADATA
configure_gpu-0.1.dist-info/WHEEL
configure_gpu-0.1.dist-info/top_level.txt
configure_gpu-0.1.dist-info/RECORD
