Metadata-Version: 2.1
Name: configure-gpu
Version: 0.1
Summary: a package for allocating tensorflow gpu memory use in python
Home-page: https://github.com/kongaevans/configure_gpu
Author: Evans Kiplagat
Author-email: evanskiplagat3@gmail.com
License: MIT
Platform: UNKNOWN
